{
  "header": {
    "logo": "/assets/logo.png",
    "navLinks": [
      {
        "name": "home",
        "href": "/"
      },
      {
        "name": "sobre mim",
        "href": "/about"
      },
      {
        "name": "habilidades",
        "href": "/skills"
      },
      {
        "name": "projetos",
        "href": "/projects"
      },
      {
        "name": "contato",
        "href": "/contact"
      }
    ],
    "toogleMode": {
      "icon": "/assets/moon.png"
    },
    "socialMedias": [
      {
        "logo": "/assets/linkedin.png",
        "link": "https://www.linkedin.com/in/ericksnascimento/"
      },
      {
        "logo": "/assets/github.png",
        "link": "https://github.com/Erick-Nascimento"
      }
    ]
  }
}
